nucleus/__init__.py
nucleus/client.py
nucleus/nucleus.py
nucleus/utils.py
nucleus_python-0.3.0.dist-info/METADATA
nucleus_python-0.3.0.dist-info/WHEEL
nucleus_python-0.3.0.dist-info/top_level.txt
nucleus_python-0.3.0.dist-info/RECORD
