Metadata-Version: 2.1
Name: nucleus-python
Version: 0.3.0
Summary: Analytics and bug tracking for Python desktop apps
Home-page: https://github.com/nucleus-sh/nucleus-python
Author: Nucleus.sh
Author-email: hello@nucleus.sh
License: MIT License
Keywords: analytics,tracking,error,bug,crash
Platform: UNKNOWN
Classifier: Programming Language :: Python :: 3
Classifier: License :: OSI Approved :: MIT License
Classifier: Operating System :: OS Independent
Requires-Python: >3.1
Requires-Dist: websocket-client
Requires-Dist: psutil
Requires-Dist: getmac
Requires-Dist: appdirs
Requires-Dist: pickledb
